niftools_sphinx_theme/__init__.py
niftools_sphinx_theme/badges.html
niftools_sphinx_theme/comments-disqus.html
niftools_sphinx_theme/globaltoc.html
niftools_sphinx_theme/layout.html
niftools_sphinx_theme/localtoc.html
niftools_sphinx_theme/relations.html
niftools_sphinx_theme/search.html
niftools_sphinx_theme/searchbox.html
niftools_sphinx_theme/theme.conf
niftools_sphinx_theme/static/css/custom.css
niftools_sphinx_theme/static/css/theme.css
niftools_sphinx_theme/static/fonts/fa-brands-400.eot
niftools_sphinx_theme/static/fonts/fa-brands-400.svg
niftools_sphinx_theme/static/fonts/fa-brands-400.ttf
niftools_sphinx_theme/static/fonts/fa-brands-400.woff
niftools_sphinx_theme/static/fonts/fa-brands-400.woff2
niftools_sphinx_theme/static/fonts/fa-solid-900.eot
niftools_sphinx_theme/static/fonts/fa-solid-900.svg
niftools_sphinx_theme/static/fonts/fa-solid-900.ttf
niftools_sphinx_theme/static/fonts/fa-solid-900.woff
niftools_sphinx_theme/static/fonts/fa-solid-900.woff2
niftools_sphinx_theme/static/js/custom.js
niftools_sphinx_theme/static/js/theme.js
niftools_sphinx_theme-0.3.3.dist-info/LICENSE
niftools_sphinx_theme-0.3.3.dist-info/METADATA
niftools_sphinx_theme-0.3.3.dist-info/WHEEL
niftools_sphinx_theme-0.3.3.dist-info/entry_points.txt
niftools_sphinx_theme-0.3.3.dist-info/top_level.txt
niftools_sphinx_theme-0.3.3.dist-info/zip-safe
niftools_sphinx_theme-0.3.3.dist-info/RECORD
