Metadata-Version: 2.1
Name: niftools-sphinx-theme
Version: 0.3.3
Summary: A sphinx theme created to support niftools documentation
Home-page: https://github.com/TagnumElite/niftools_sphinx_theme
Author: TagnumElite
Author-email: tagnumelite@elitekast.com
License: GPLv3
Keywords: sphinx,theme,niftools
Platform: UNKNOWN
Classifier: Development Status :: 2 - Pre-Alpha
Classifier: Framework :: Sphinx
Classifier: Framework :: Sphinx :: Theme
Classifier: License :: OSI Approved :: GNU General Public License v3 (GPLv3)
Classifier: Operating System :: OS Independent
Classifier: Programming Language :: Python
Classifier: Topic :: Documentation
Classifier: Topic :: Documentation :: Sphinx
Classifier: Topic :: Software Development :: Documentation
Requires-Dist: sphinx
